ciqueue/__init__.py
ciqueue/distributed.py
ciqueue/file.py
ciqueue/pytest.py
ciqueue/pytest_report.py
ciqueue/static.py
ciqueue/_pytest/__init__.py
ciqueue/_pytest/outcomes.py
ciqueue/_pytest/test_queue.py
ciqueue/redis/acknowledge.lua
ciqueue/redis/requeue.lua
ciqueue/redis/reserve.lua
ciqueue/redis/reserve_lost.lua
ciqueue-0.1.dist-info/DESCRIPTION.rst
ciqueue-0.1.dist-info/METADATA
ciqueue-0.1.dist-info/metadata.json
ciqueue-0.1.dist-info/RECORD
ciqueue-0.1.dist-info/top_level.txt
ciqueue-0.1.dist-info/WHEEL
