Metadata-Version: 2.0
Name: ciqueue
Version: 0.1
Summary: UNKNOWN
Home-page: UNKNOWN
Author: UNKNOWN
Author-email: UNKNOWN
License: UNKNOWN
Platform: UNKNOWN
Requires-Dist: dill (>=0.2.7)
Requires-Dist: pytest (<=3.3.1,>=2.7)
Requires-Dist: redis (>=2.10.5)
Requires-Dist: tblib (>=1.3.2)
Requires-Dist: uritools (>=2.0.0)
Requires-Dist: future (>=0.16.0)
Provides-Extra: test
Requires-Dist: tox (==2.9.1); extra == 'test'
Requires-Dist: shopify-python (==0.4.1); extra == 'test'
Requires-Dist: pycodestyle (==2.3.0); extra == 'test'
